pyprojectize.py
pyprojectize-1a7.dist-info/METADATA
pyprojectize-1a7.dist-info/WHEEL
pyprojectize-1a7.dist-info/entry_points.txt
pyprojectize-1a7.dist-info/licenses/LICENSE
pyprojectize-1a7.dist-info/RECORD
