Metadata-Version: 2.4
Name: pyprojectize
Version: 1a7
Summary: Converts a Fedora RPM spec file from %py3_build etc. to %pyproject macros
Project-URL: Homepage, https://github.com/hroncok/pyprojectize/
Project-URL: Issues, https://github.com/hroncok/pyprojectize/issues
Author-email: Miro Hrončok <miro@hroncok.cz>
License-Expression: MIT-0
License-File: LICENSE
Requires-Python: >=3.12
Requires-Dist: packaging
Requires-Dist: specfile
Provides-Extra: test
Requires-Dist: pytest; extra == 'test'
